{
    "lectures":[
        {
            "src":"https://cdn.inflearn.com/public/courses/325630/cover/56f635a3-3a44-4096-a16b-453ea1696b1a/325630-eng.png",
            "title":"스프링 입문 - 코드로 배우는 스프링부트, 웹 MVC, DB 접근 기술",
            "instruct":"김영한",
            "rating":"⭐ ⭐ ⭐ ⭐ ⭐",
            "ratingNum":4778,
            "tagNum":"+65700명",
            "tagUpdate":"업데이트",
            "backTitle":"스프링 입문 - 코드로 배우는 스프링부트, 웹 MVC, DB 접근 기술",
            "level":"초급",
            "category":"백엔드, 웹 개발",
            "skill":"Java, Spring, MVC"
        },
        {
            "src":"https://cdn.inflearn.com/public/courses/330264/cover/5d40d110-c372-42ef-ad06-fe01257225cc/330264-eng.png",
            "title":"실전! 스프링부트 상품-주문 API 개발로 알아보는 TDD",
            "instruct":"이중석",
            "rating":"⭐ ⭐ ⭐ ⭐ ⭐",
            "ratingNum":8,
            "tagNum":"+500명",
            "tagUpdate":"새강의",
            "backTitle":"실전! 스프링부트 상품-주문 API 개발로 알아보는 TDD",
            "level":"초급",
            "category":"백엔드, 웹 개발",
            "skill":"Java, Spring, MVC"
        },
        {
            "src":"https://cdn.inflearn.com/public/courses/329211/cover/ea485515-6665-4e5c-acd7-157c2b8b08f3/infcon-apply-main.png",
            "title":"인프콘 2022 다시보기",
            "instruct":"인프런",
            "rating":"⭐ ⭐ ⭐ ⭐ ⭐",
            "ratingNum":28,
            "tagNum":"+14000명",
            "tagUpdate":null,
            "backTitle":"인프콘 2022 다시보기",
            "level":"입문",
            "category":"기술",
            "skill":""
        },
        {
            "src":"https://cdn.inflearn.com/public/courses/328866/cover/174035a3-ca6b-48cd-b122-c88df540cb04/처음_만난_리액트_v2_cover_inflearn.png",
            "title":"처음 만난 리액트(React)",
            "instruct":"Inje Lee(소플)",
            "rating":"⭐ ⭐ ⭐ ⭐ ⭐",
            "ratingNum":104,
            "tagNum":"+5100명",
            "tagUpdate":null,
            "backTitle":"처음 만난 리액트(React)",
            "level":"초급",
            "category":"프론트엔드, 웹 개발",
            "skill":"Java, React"
        },
        {
            "src":"https://cdn.inflearn.com/public/courses/328577/cover/d7cd62c2-db07-45d8-af8d-a3fa728cd8e7/inflearn-logo.jpg",
            "title":"[코드팩토리] [입문] Dart 언어 4시간만에 완전정복",
            "instruct":"코드팩토리",
            "rating":"⭐ ⭐ ⭐ ⭐ ⭐",
            "ratingNum":285,
            "tagNum":"+3700명",
            "tagUpdate":null,
            "backTitle":"[코드팩토리] [입문] Dart 언어 4시간만에 완전정복",
            "level":"입문",
            "category":"프로그래밍 언어",
            "skill":"Flutter, 객체지향 언어"
        }
    ],
    "courses":[
        {
            "src":"https://cdn.inflearn.com/public/courses/329922/cover/364e7406-3569-437b-b719-7f146cad3d60/thumbnail-js.png",
            "title":"[인프런x코드캠프] 훈훈한 Javascript",
            "instruct":"코드캠프",
            "rating":"⭐⭐⭐⭐⭐",
            "ratingNum":33,
            "price":"₩22,000",
            "tag1":"+2200명",
            "del":false,
            "backTitle":"[인프런x코드캠프] 훈훈한 Javascript",
            "level":"입문",
            "category":"프로그래밍 언어",
            "skill":"JavaScript"
        },
        {
            "src":"https://cdn.inflearn.com/public/courses/329913/cover/eee923cc-911b-4c2d-a445-9fddee8e5992/thumbnail-precamp.png",
            "title":"[인프런x코드캠프] 시작은 프리캠프",
            "instruct":"코드캠프",
            "rating":"⭐⭐⭐⭐⭐",
            "ratingNum":43,
            "price":"₩22,000",
            "del":false,
            "backTitle":"[인프런x코드캠프] 시작은 프리캠프",
            "level":"입문",
            "category":"프론트엔드, 웹 개발",
            "skill":"JavaScript, HTML/CSS"
        },
        {
            "src":"https://cdn.inflearn.com/public/courses/329755/cover/6fc3f9be-8cc1-42a3-8b6a-b34d91352df2/JavaScript--IFL.png",
            "title":"제대로 파는 자바스크립트(JavaScript) - by 얄코",
            "instruct":"얄팍한 코딩사전",
            "rating":"⭐⭐⭐⭐⭐",
            "ratingNum":6,
            "price":"₩41,250",
            "delPrice":"₩55,000", 
            "del":true, "tag3":"할인중", "tag2":"업데이트", "tag1":"+600명",
            "backTitle":"제대로 파는 자바스크립트(JavaScript) - by 얄코",
            "level":"초급",
            "category":"프론트엔드, 웹 개발",
            "skill":"JavaScript"
        },
        {
            "src":"https://cdn.inflearn.com/public/courses/326377/cover/f0f0b7b0-a4f1-4ca4-b609-c026c7d5bd20/js_algorithm_best.png",
            "title":"자바스크립트 알고리즘 문제풀이 입문(코딩테스트 대비)",
            "instruct":"김태원",
            "rating":"⭐⭐⭐⭐⭐",
            "ratingNum":150,
            "price":"₩66,000",
            "tag1":"+3600명",
            "del":false,
            "backTitle":"자바스크립트 알고리즘 문제풀이 입문(코딩테스트 대비)",
            "level":"입문",
            "category":"알고리즘, 자료구조",
            "skill":"JavaScript, 코딩 테스트"
        },
        {
            "src":"https://cdn.inflearn.com/public/courses/329534/cover/76d5fd7f-3e76-4801-bb8f-523d10ff5829/329534-eng.jpg",
            "title":"외워서 끝내는 네트워크 핵심이론 - 기초",
            "instruct":"널널한 개발자",
            "rating":"⭐⭐⭐⭐⭐",
            "ratingNum":37,
            "price":"₩77,000",
            "tag1":"+900명",
            "del":false,
            "backTitle":"외워서 끝내는 네트워크 핵심이론 - 기초",
            "level":"입문",
            "category":"네트워크, 교양, 기초",
            "skill":"네트워크"
        },
        {
            "src":"https://cdn.inflearn.com/public/courses/329480/cover/dc203b59-e468-4cda-9368-d72794c1213e/329480-eng.jpg",
            "title":"CAN 통신 - 자동차 신입이 알아야 할 모든 것",
            "instruct":"존버매니아",
            "rating":"⭐⭐⭐⭐⭐",
            "ratingNum":5,
            "price":"₩55,000",
            "tag1":"+100명",
            "del":false,
            "backTitle":"CAN 통신 - 자동차 신입이 알아야 할 모든 것",
            "level":"입문",
            "category":"임베디드, IOT",
            "skill":"CAN"
        },
        {
            "src":"https://cdn.inflearn.com/public/courses/329398/cover/5e613ac4-cfe3-4a97-ac6d-929d9cd49647/329398-eng.jpg",
            "title":"카프카 완벽 가이드 - 코어편",
            "instruct":"권철민",
            "rating":"⭐⭐⭐⭐⭐",
            "ratingNum":15,
            "price":"₩99,000",
            "tag1":"+400명",
            "del":false,
            "backTitle":"카프카 완벽 가이드 - 코어편",
            "level":"중급이상",
            "category":"데이터 수집, 처리, 데브옵스",
            "skill":"Kafka, 데이터 엔지니어링"
        },
        {
            "src":"https://cdn.inflearn.com/public/courses/329328/cover/e7e1af16-f2d9-4c23-9447-49039b837813/329328-eng.jpg",
            "title":"[입문자를 위한 UE5] Part3. 언리얼 엔진 3D 게임 개발 입문",
            "instruct":"Rookiss",
            "rating":"⭐⭐⭐⭐⭐",
            "ratingNum":7,
            "price":"₩55,000",
            "tag1":"+200명",
            "del":false,
            "backTitle":"[입문자를 위한 UE5] Part3. 언리얼 엔진 3D 게임 개발 입문",
            "level":"초급",
            "category":"게임 개발, 게임 프로그래밍",
            "skill":"Unreal, UE Blueprint"
        }

    ],
    "mentors":[
        {
            "src":"https://cdn.inflearn.com/public/users/thumbnails/36294/c14ef375-cddf-4d75-82d9-055109c79eb6",
            "title":"신입~주니어 개발자 취직, 이력서&프론트엔드 상담 및 고민, 커리어 및 로드맵 설계",
            "header1":"직무",
            "content1":"프론트엔드/웹퍼블리셔",
            "header2":"경력",
            "content2":"미들 (4~8년)",
            "rating":"5.0",
            "name":"장현석"
        },
        {
            "src":"https://cdn.inflearn.com/public/users/thumbnails/1044033/d3a5c784-c97b-4879-a97f-6a0fc06ebf13",
            "title":"NLP+AI 분야 커리어 컨설팅 / 논문 함께 읽기",
            "header1":"직무",
            "content1":"데이터 사이언티스트",
            "header2":"경력",
            "content2":"Lead 레벨",
            "header3":"현직",
            "content3":"네이버",
            "rating":"5.0",
            "name":"Jaewook Kang"
        },
        {
            "src":"https://cdn.inflearn.com/public/users/thumbnails/105536/6bc90553-bfdd-4905-ba9c-4d8b02fb96d9",
            "title":"백엔드 엔지니어 커리어 멘토링/코드리뷰/이력서 첨삭",
            "header1":"직무",
            "content1":"백엔드/서버 개발자",
            "header2":"경력",
            "content2":"미들 (4~8년)",
            "header3":"현직",
            "content3":"카카오페이",
            "rating":"5.0",
            "name":"Sun"
        },
        {
            "src":"https://cdn.inflearn.com/public/users/thumbnails/117609/09c882a3-a8af-4f14-a19b-9a81256c39d0",
            "title":"back-end 신입/주니어 개발자 서비스 회사 취업설계 | 이직 | 기술 면접 상담",
            "header1":"직무",
            "content1":"백엔드/서버 개발자",
            "header2":"경력",
            "content2":"미들 (4~8년)",
            "header3":"현직",
            "content3":"네카라중 한곳",
            "rating":"5.0",
            "name":"incu"
        },
        {
            "src":"https://cdn.inflearn.com/public/users/thumbnails/1115642/0ba80207-ceb2-4356-8761-2b3cecc3b694",
            "title":"백엔드 개발자 이직/취업",
            "header1":"직무",
            "content1":"백엔드/서버 개발자",
            "header2":"경력",
            "content2":"Lead 레벨",
            "header3":"현직",
            "content3":"스타트업",
            "rating":"none",
            "name":"케인"
        },
        {
            "src":"https://cdn.inflearn.com/public/users/thumbnails/209928/a46703da-f0ba-4403-abd6-b8f5c1473652",
            "title":"개발자로서 커리어 혹은 DevOps기술",
            "header1":"",
            "content1":"",
            "header2":"",
            "content2":"",
            "rating":"5.0",
            "name":"subicura"
        },
        {
            "src":"https://cdn.inflearn.com/public/users/thumbnails/199520/ed9c8718-ef2a-4ef0-812c-c85627bb2a1b",
            "title":"백엔드 개발자의 성장을 위한 멘토링 & 코드 리뷰" ,
            "header1":"직무",
            "content1":"백엔드/서버 개발자",
            "header2":"경력",
            "content2":"미들 (4~8년)",
            "header3":"현직",
            "content3":"컬리페이",
            "rating":"5.0",
            "name":"Byung Hyun Choi"
        },
        {
            "src":"https://cdn.inflearn.com/public/users/thumbnails/581610/9946f92b-216b-400c-8c1f-e9029139a871",
            "title":"비전공자의 1년만에 네카라쿠배 합격방법",
            "header1":"직무",
            "content1":"백엔드/서버 개발자",
            "header2":"경력",
            "content2":"미들 (4~8년)",
            "header3":"현직",
            "content3":"네카라쿠배",
            "rating":"5.0",
            "name":"최연찬"
        }
    ]
}